Metadata-Version: 2.4
Name: kuest-py-builder-signing-sdk
Version: 0.0.1
Summary: Python builder signing sdk
Home-page: https://github.com/kuestcom/py-builder-signing-sdk
Author: Kuest Engineering
Author-email: engineering@kuest.com
Maintainer: Kuest Engineering
Maintainer-email: engineering@kuest.com
Project-URL: Bug Tracker, https://github.com/kuestcom/py-builder-signing-sdk/issues
Classifier: Programming Language :: Python :: 3
Classifier: License :: OSI Approved :: MIT License
Classifier: Operating System :: OS Independent
Requires-Python: >=3.9.10
License-File: LICENSE
Requires-Dist: python-dotenv
Requires-Dist: requests
Dynamic: author
Dynamic: author-email
Dynamic: classifier
Dynamic: description
Dynamic: description-content-type
Dynamic: home-page
Dynamic: license-file
Dynamic: maintainer
Dynamic: maintainer-email
Dynamic: project-url
Dynamic: requires-dist
Dynamic: requires-python
Dynamic: summary
